{"bases":[{"base":null,"index":27728,"name":"AnimFeature"},{"base":null,"index":9320,"name":"IScriptable"}],"fields":[],"isAbstract":false,"isFinal":false,"isNative":true,"isStruct":false,"methods":[{"isCallback":false,"isExec":false,"isFinal":true,"isNative":true,"isStatic":false,"name":"SetLoopDuration","parameters":[{"isOptional":false,"isOut":false,"name":"loopDuration","tag":"Parameter","type":{"kind":"Prim","name":"Float","tag":"Type"}}],"returnType":null,"source":null,"tag":"Function","visibility":"public"},{"isCallback":false,"isExec":false,"isFinal":true,"isNative":true,"isStatic":false,"name":"SetNumLoops","parameters":[{"isOptional":false,"isOut":false,"name":"numLoops","tag":"Parameter","type":{"kind":"Prim","name":"Int32","tag":"Type"}}],"returnType":null,"source":null,"tag":"Function","visibility":"public"},{"isCallback":false,"isExec":false,"isFinal":true,"isNative":true,"isStatic":false,"name":"SetActive","parameters":[{"isOptional":false,"isOut":false,"name":"isActive","tag":"Parameter","type":{"kind":"Prim","name":"Bool","tag":"Type"}}],"returnType":null,"source":null,"tag":"Function","visibility":"public"}],"name":"AnimFeature_LoopableAction","tag":"Class","visibility":"public"}