{"bases":[{"base":null,"index":9320,"name":"IScriptable"}],"fields":[{"isConst":false,"isEdit":false,"isInline":false,"isNative":false,"isPersistent":false,"isRep":false,"name":"equipmentArea","tag":"Field","type":{"index":5472,"kind":"Class","name":"gamedataEquipmentArea","tag":"Type"}},{"isConst":false,"isEdit":false,"isInline":false,"isNative":false,"isPersistent":false,"isRep":false,"name":"items","tag":"Field","type":{"inner":{"index":19848,"kind":"Class","name":"InventoryItemData","tag":"Type"},"kind":"Array","tag":"Type"}}],"isAbstract":false,"isFinal":false,"isNative":false,"isStruct":false,"methods":[],"name":"ItemPreferredAreaItems","tag":"Class","visibility":"public"}