{"bases":[{"base":null,"index":87336,"name":"ToggleController"},{"base":null,"index":84933,"name":"inkToggleController"},{"base":null,"index":64885,"name":"inkButtonController"},{"base":null,"index":34538,"name":"inkLogicController"},{"base":null,"index":18382,"name":"inkILogicController"},{"base":null,"index":9320,"name":"IScriptable"}],"fields":[],"isAbstract":false,"isFinal":false,"isNative":false,"isStruct":false,"methods":[{"isCallback":false,"isExec":false,"isFinal":false,"isNative":false,"isStatic":false,"name":"GetLabelKey;","parameters":[],"returnType":{"kind":"Prim","name":"String","tag":"Type"},"source":"cyberpunk/UI/inventory/ripperdocFilter.script","tag":"Function","visibility":"public"},{"isCallback":false,"isExec":false,"isFinal":false,"isNative":false,"isStatic":false,"name":"GetIcon;","parameters":[],"returnType":{"kind":"Prim","name":"String","tag":"Type"},"source":"cyberpunk/UI/inventory/ripperdocFilter.script","tag":"Function","visibility":"public"}],"name":"RipperdocFilterToggleController","tag":"Class","visibility":"public"}