{"bases":[{"base":null,"index":89164,"name":"ItemTooltipModuleController"},{"base":null,"index":34517,"name":"inkLogicController"},{"base":null,"index":18376,"name":"inkILogicController"},{"base":null,"index":9314,"name":"IScriptable"}],"fields":[{"isConst":false,"isEdit":true,"isInline":false,"isNative":false,"isPersistent":false,"isRep":false,"name":"m_container","tag":"Field","type":{"index":35000,"kind":"Class","name":"inkImageRef","tag":"Type"}},{"isConst":false,"isEdit":true,"isInline":false,"isNative":false,"isPersistent":false,"isRep":false,"name":"m_icon","tag":"Field","type":{"index":35000,"kind":"Class","name":"inkImageRef","tag":"Type"}},{"isConst":false,"isEdit":true,"isInline":false,"isNative":false,"isPersistent":false,"isRep":false,"name":"m_iconicLines","tag":"Field","type":{"index":35000,"kind":"Class","name":"inkImageRef","tag":"Type"}},{"isConst":false,"isEdit":true,"isInline":false,"isNative":false,"isPersistent":false,"isRep":false,"name":"m_transmogged","tag":"Field","type":{"index":35000,"kind":"Class","name":"inkImageRef","tag":"Type"}},{"isConst":false,"isEdit":false,"isInline":false,"isNative":false,"isPersistent":false,"isRep":false,"name":"iconsNameResolver","tag":"Field","type":{"inner":{"index":60413,"kind":"Class","name":"IconsNameResolver","tag":"Type"},"kind":"Ref","tag":"Type"}}],"isAbstract":false,"isFinal":false,"isNative":false,"isStruct":false,"methods":[{"isCallback":true,"isExec":false,"isFinal":false,"isNative":false,"isStatic":false,"name":"OnInitialize","parameters":[],"returnType":{"kind":"Prim","name":"Bool","tag":"Type"},"source":"cyberpunk/UI/tooltips/itemTooltipController.script","tag":"Function","visibility":"protected"},{"isCallback":false,"isExec":false,"isFinal":false,"isNative":false,"isStatic":false,"name":"Update;MinimalItemTooltipData","parameters":[{"isOptional":false,"isOut":false,"name":"data","tag":"Parameter","type":{"inner":{"index":68993,"kind":"Class","name":"MinimalItemTooltipData","tag":"Type"},"kind":"Ref","tag":"Type"}}],"returnType":null,"source":"cyberpunk/UI/tooltips/itemTooltipController.script","tag":"Function","visibility":"public"},{"isCallback":true,"isExec":false,"isFinal":false,"isNative":false,"isStatic":false,"name":"OnIconCallback","parameters":[{"isOptional":false,"isOut":false,"name":"e","tag":"Parameter","type":{"inner":{"index":87046,"kind":"Class","name":"iconAtlasCallbackData","tag":"Type"},"kind":"Ref","tag":"Type"}}],"returnType":{"kind":"Prim","name":"Bool","tag":"Type"},"source":"cyberpunk/UI/tooltips/itemTooltipController.script","tag":"Function","visibility":"protected"},{"isCallback":false,"isExec":false,"isFinal":true,"isNative":false,"isStatic":false,"name":"GetIconPath;MinimalItemTooltipDataItem_Record","parameters":[{"isOptional":false,"isOut":false,"name":"data","tag":"Parameter","type":{"inner":{"index":68993,"kind":"Class","name":"MinimalItemTooltipData","tag":"Type"},"kind":"Ref","tag":"Type"}},{"isOptional":true,"isOut":false,"name":"itemRecord","tag":"Parameter","type":{"inner":{"index":12060,"kind":"Class","name":"Item_Record","tag":"Type"},"kind":"WeakRef","tag":"Type"}}],"returnType":{"kind":"Prim","name":"CName","tag":"Type"},"source":"cyberpunk/UI/tooltips/itemTooltipController.script","tag":"Function","visibility":"private"},{"isCallback":false,"isExec":false,"isFinal":true,"isNative":false,"isStatic":false,"name":"GetIconScale;MinimalItemTooltipDatagamedataEquipmentArea","parameters":[{"isOptional":false,"isOut":false,"name":"data","tag":"Parameter","type":{"inner":{"index":68993,"kind":"Class","name":"MinimalItemTooltipData","tag":"Type"},"kind":"Ref","tag":"Type"}},{"isOptional":false,"isOut":false,"name":"equipmentArea","tag":"Parameter","type":{"index":5137,"kind":"Class","name":"gamedataEquipmentArea","tag":"Type"}}],"returnType":{"index":18458,"kind":"Class","name":"Vector2","tag":"Type"},"source":"cyberpunk/UI/tooltips/itemTooltipController.script","tag":"Function","visibility":"private"},{"isCallback":false,"isExec":false,"isFinal":false,"isNative":false,"isStatic":false,"name":"NEW_Update;UIInventoryItem","parameters":[{"isOptional":false,"isOut":false,"name":"data","tag":"Parameter","type":{"inner":{"index":69461,"kind":"Class","name":"UIInventoryItem","tag":"Type"},"kind":"WeakRef","tag":"Type"}}],"returnType":null,"source":"cyberpunk/UI/tooltips/itemTooltipController.script","tag":"Function","visibility":"public"},{"isCallback":true,"isExec":false,"isFinal":false,"isNative":false,"isStatic":false,"name":"OnNEW_IconCallback","parameters":[{"isOptional":false,"isOut":false,"name":"e","tag":"Parameter","type":{"inner":{"index":87046,"kind":"Class","name":"iconAtlasCallbackData","tag":"Type"},"kind":"Ref","tag":"Type"}}],"returnType":{"kind":"Prim","name":"Bool","tag":"Type"},"source":"cyberpunk/UI/tooltips/itemTooltipController.script","tag":"Function","visibility":"protected"},{"isCallback":false,"isExec":false,"isFinal":true,"isNative":false,"isStatic":false,"name":"NEW_GetIconScale;gamedataEquipmentArea","parameters":[{"isOptional":false,"isOut":false,"name":"equipmentArea","tag":"Parameter","type":{"index":5137,"kind":"Class","name":"gamedataEquipmentArea","tag":"Type"}}],"returnType":{"index":18458,"kind":"Class","name":"Vector2","tag":"Type"},"source":"cyberpunk/UI/tooltips/itemTooltipController.script","tag":"Function","visibility":"private"}],"name":"ItemTooltipIconModule","tag":"Class","visibility":"public"}