{"bases":[{"base":null,"index":22735,"name":"inkGameController"},{"base":null,"index":22723,"name":"worlduiIGameController"},{"base":null,"index":22186,"name":"inkIGameController"},{"base":null,"index":11333,"name":"IScriptable"}],"fields":[{"isConst":false,"isEdit":false,"isInline":false,"isNative":true,"isPersistent":false,"isRep":false,"name":"adjustedScreenPosition","tag":"Field","type":{"index":22278,"kind":"Class","name":"Vector2","tag":"Type"}},{"isConst":false,"isEdit":false,"isInline":false,"isNative":true,"isPersistent":false,"isRep":false,"name":"maxHealth","tag":"Field","type":{"kind":"Prim","name":"Float","tag":"Type"}},{"isConst":false,"isEdit":false,"isInline":false,"isNative":true,"isPersistent":false,"isRep":false,"name":"currentHealth","tag":"Field","type":{"kind":"Prim","name":"Float","tag":"Type"}},{"isConst":false,"isEdit":false,"isInline":false,"isNative":true,"isPersistent":false,"isRep":false,"name":"lastHealth","tag":"Field","type":{"kind":"Prim","name":"Float","tag":"Type"}},{"isConst":false,"isEdit":false,"isInline":false,"isNative":false,"isPersistent":false,"isRep":false,"name":"m_currentSway","tag":"Field","type":{"index":22278,"kind":"Class","name":"Vector2","tag":"Type"}},{"isConst":false,"isEdit":true,"isInline":false,"isNative":false,"isPersistent":false,"isRep":false,"name":"m_breachCanvasWRef","tag":"Field","type":{"index":54543,"kind":"Class","name":"inkWidgetRef","tag":"Type"}},{"isConst":false,"isEdit":true,"isInline":false,"isNative":false,"isPersistent":false,"isRep":false,"name":"m_strokeFgRef","tag":"Field","type":{"index":128200,"kind":"Class","name":"inkBorderRef","tag":"Type"}},{"isConst":false,"isEdit":true,"isInline":false,"isNative":false,"isPersistent":false,"isRep":false,"name":"m_strokeBgRef","tag":"Field","type":{"index":128200,"kind":"Class","name":"inkBorderRef","tag":"Type"}},{"isConst":false,"isEdit":true,"isInline":false,"isNative":false,"isPersistent":false,"isRep":false,"name":"m_waveStrokeRef","tag":"Field","type":{"index":128200,"kind":"Class","name":"inkBorderRef","tag":"Type"}},{"isConst":false,"isEdit":true,"isInline":false,"isNative":false,"isPersistent":false,"isRep":false,"name":"m_fillRef","tag":"Field","type":{"index":54543,"kind":"Class","name":"inkWidgetRef","tag":"Type"}},{"isConst":false,"isEdit":true,"isInline":false,"isNative":false,"isPersistent":false,"isRep":false,"name":"m_textScaleWidgetRef","tag":"Field","type":{"index":55220,"kind":"Class","name":"inkCompoundRef","tag":"Type"}},{"isConst":false,"isEdit":true,"isInline":false,"isNative":false,"isPersistent":false,"isRep":false,"name":"m_xTextRef","tag":"Field","type":{"index":55061,"kind":"Class","name":"inkTextRef","tag":"Type"}},{"isConst":false,"isEdit":true,"isInline":false,"isNative":false,"isPersistent":false,"isRep":false,"name":"m_yTextRef","tag":"Field","type":{"index":55061,"kind":"Class","name":"inkTextRef","tag":"Type"}},{"isConst":false,"isEdit":true,"isInline":false,"isNative":false,"isPersistent":false,"isRep":false,"name":"m_errorTextRef","tag":"Field","type":{"index":55061,"kind":"Class","name":"inkTextRef","tag":"Type"}},{"isConst":false,"isEdit":true,"isInline":false,"isNative":false,"isPersistent":false,"isRep":false,"name":"m_strokeThicknessPercent","tag":"Field","type":{"kind":"Prim","name":"Float","tag":"Type"}},{"isConst":false,"isEdit":true,"isInline":false,"isNative":false,"isPersistent":false,"isRep":false,"name":"m_minThickness","tag":"Field","type":{"kind":"Prim","name":"Float","tag":"Type"}},{"isConst":false,"isEdit":true,"isInline":false,"isNative":false,"isPersistent":false,"isRep":false,"name":"m_maxThickness","tag":"Field","type":{"kind":"Prim","name":"Float","tag":"Type"}},{"isConst":false,"isEdit":true,"isInline":false,"isNative":false,"isPersistent":false,"isRep":false,"name":"m_minTextScale","tag":"Field","type":{"kind":"Prim","name":"Float","tag":"Type"}},{"isConst":false,"isEdit":true,"isInline":false,"isNative":false,"isPersistent":false,"isRep":false,"name":"m_maxTextScale","tag":"Field","type":{"kind":"Prim","name":"Float","tag":"Type"}},{"isConst":false,"isEdit":true,"isInline":false,"isNative":false,"isPersistent":false,"isRep":false,"name":"m_maxRadius","tag":"Field","type":{"kind":"Prim","name":"Float","tag":"Type"}},{"isConst":false,"isEdit":false,"isInline":false,"isNative":false,"isPersistent":false,"isRep":false,"name":"m_minRadiusForFluff","tag":"Field","type":{"kind":"Prim","name":"Float","tag":"Type"}},{"isConst":false,"isEdit":false,"isInline":false,"isNative":false,"isPersistent":false,"isRep":false,"name":"m_previousAlmostTimeout","tag":"Field","type":{"kind":"Prim","name":"Bool","tag":"Type"}},{"isConst":false,"isEdit":false,"isInline":false,"isNative":false,"isPersistent":false,"isRep":false,"name":"m_cwBreachCallbackHandle","tag":"Field","type":{"inner":{"index":123449,"kind":"Class","name":"CallbackHandle","tag":"Type"},"kind":"Ref","tag":"Type"}},{"isConst":false,"isEdit":false,"isInline":false,"isNative":false,"isPersistent":false,"isRep":false,"name":"m_weaponSwayCallbackHandle","tag":"Field","type":{"inner":{"index":123449,"kind":"Class","name":"CallbackHandle","tag":"Type"},"kind":"Ref","tag":"Type"}},{"isConst":false,"isEdit":false,"isInline":false,"isNative":false,"isPersistent":false,"isRep":false,"name":"m_introAnimationProxy","tag":"Field","type":{"inner":{"index":54304,"kind":"Class","name":"inkAnimProxy","tag":"Type"},"kind":"Ref","tag":"Type"}},{"isConst":false,"isEdit":false,"isInline":false,"isNative":false,"isPersistent":false,"isRep":false,"name":"m_showAnimationProxy","tag":"Field","type":{"inner":{"index":54304,"kind":"Class","name":"inkAnimProxy","tag":"Type"},"kind":"Ref","tag":"Type"}},{"isConst":false,"isEdit":false,"isInline":false,"isNative":false,"isPersistent":false,"isRep":false,"name":"m_timeoutAnimationProxy","tag":"Field","type":{"inner":{"index":54304,"kind":"Class","name":"inkAnimProxy","tag":"Type"},"kind":"Ref","tag":"Type"}}],"isAbstract":false,"isFinal":false,"isNative":true,"isStruct":false,"methods":[{"isCallback":false,"isExec":false,"isFinal":true,"isNative":true,"isStatic":false,"name":"ResetCodeAnims","parameters":[],"returnType":null,"source":null,"tag":"Function","visibility":"public"},{"isCallback":false,"isExec":false,"isFinal":true,"isNative":true,"isStatic":false,"name":"GotoEndAndStopMoveAnim","parameters":[{"isOptional":false,"isOut":false,"name":"fireCallback","tag":"Parameter","type":{"kind":"Prim","name":"Bool","tag":"Type"}}],"returnType":null,"source":null,"tag":"Function","visibility":"public"},{"isCallback":false,"isExec":false,"isFinal":true,"isNative":true,"isStatic":false,"name":"GotoEndAndStopSizeAnim","parameters":[{"isOptional":false,"isOut":false,"name":"fireCallback","tag":"Parameter","type":{"kind":"Prim","name":"Bool","tag":"Type"}}],"returnType":null,"source":null,"tag":"Function","visibility":"public"},{"isCallback":false,"isExec":false,"isFinal":true,"isNative":true,"isStatic":false,"name":"BeginMoveAnim","parameters":[{"isOptional":false,"isOut":false,"name":"moveSpeed","tag":"Parameter","type":{"kind":"Prim","name":"Float","tag":"Type"}}],"returnType":null,"source":null,"tag":"Function","visibility":"public"},{"isCallback":false,"isExec":false,"isFinal":true,"isNative":true,"isStatic":false,"name":"BeginSizeAnim","parameters":[{"isOptional":false,"isOut":false,"name":"sizeSpeed","tag":"Parameter","type":{"kind":"Prim","name":"Float","tag":"Type"}}],"returnType":null,"source":null,"tag":"Function","visibility":"public"},{"isCallback":false,"isExec":false,"isFinal":true,"isNative":true,"isStatic":false,"name":"GetMoveAnimPercent","parameters":[],"returnType":{"kind":"Prim","name":"Float","tag":"Type"},"source":null,"tag":"Function","visibility":"public"},{"isCallback":false,"isExec":false,"isFinal":true,"isNative":true,"isStatic":false,"name":"GetSizeAnimPercent","parameters":[],"returnType":{"kind":"Prim","name":"Float","tag":"Type"},"source":null,"tag":"Function","visibility":"public"},{"isCallback":false,"isExec":false,"isFinal":true,"isNative":true,"isStatic":false,"name":"UpdateHealthDepletion","parameters":[],"returnType":null,"source":null,"tag":"Function","visibility":"public"},{"isCallback":true,"isExec":false,"isFinal":false,"isNative":false,"isStatic":false,"name":"OnInitialize","parameters":[],"returnType":{"kind":"Prim","name":"Bool","tag":"Type"},"source":"cyberpunk/UI/hud/cyberwareBreach/cyberwareBreachGameController.script","tag":"Function","visibility":"protected"},{"isCallback":true,"isExec":false,"isFinal":false,"isNative":false,"isStatic":false,"name":"OnUninitialize","parameters":[],"returnType":{"kind":"Prim","name":"Bool","tag":"Type"},"source":"cyberpunk/UI/hud/cyberwareBreach/cyberwareBreachGameController.script","tag":"Function","visibility":"protected"},{"isCallback":false,"isExec":false,"isFinal":true,"isNative":false,"isStatic":false,"name":"RegisterBlackboardCallbacks;","parameters":[],"returnType":null,"source":"cyberpunk/UI/hud/cyberwareBreach/cyberwareBreachGameController.script","tag":"Function","visibility":"private"},{"isCallback":false,"isExec":false,"isFinal":true,"isNative":false,"isStatic":false,"name":"UnregisterBlackboardCallbacks;","parameters":[],"returnType":null,"source":"cyberpunk/UI/hud/cyberwareBreach/cyberwareBreachGameController.script","tag":"Function","visibility":"private"},{"isCallback":true,"isExec":false,"isFinal":false,"isNative":false,"isStatic":false,"name":"OnBreachDataChanged","parameters":[{"isOptional":false,"isOut":false,"name":"value","tag":"Parameter","type":{"kind":"Prim","name":"Variant","tag":"Type"}}],"returnType":{"kind":"Prim","name":"Bool","tag":"Type"},"source":"cyberpunk/UI/hud/cyberwareBreach/cyberwareBreachGameController.script","tag":"Function","visibility":"protected"},{"isCallback":true,"isExec":false,"isFinal":false,"isNative":false,"isStatic":false,"name":"OnSway","parameters":[{"isOptional":false,"isOut":false,"name":"pos","tag":"Parameter","type":{"index":22278,"kind":"Class","name":"Vector2","tag":"Type"}}],"returnType":{"kind":"Prim","name":"Bool","tag":"Type"},"source":"cyberpunk/UI/hud/cyberwareBreach/cyberwareBreachGameController.script","tag":"Function","visibility":"protected"},{"isCallback":false,"isExec":false,"isFinal":true,"isNative":false,"isStatic":false,"name":"UpdateState;Bool","parameters":[{"isOptional":false,"isOut":false,"name":"visible","tag":"Parameter","type":{"kind":"Prim","name":"Bool","tag":"Type"}}],"returnType":null,"source":"cyberpunk/UI/hud/cyberwareBreach/cyberwareBreachGameController.script","tag":"Function","visibility":"private"},{"isCallback":false,"isExec":false,"isFinal":true,"isNative":false,"isStatic":false,"name":"ChangeScreenPosition;Vector2","parameters":[{"isOptional":false,"isOut":false,"name":"screenPosition","tag":"Parameter","type":{"index":22278,"kind":"Class","name":"Vector2","tag":"Type"}}],"returnType":null,"source":"cyberpunk/UI/hud/cyberwareBreach/cyberwareBreachGameController.script","tag":"Function","visibility":"private"},{"isCallback":false,"isExec":false,"isFinal":true,"isNative":false,"isStatic":false,"name":"ChangeScreenSize;Float","parameters":[{"isOptional":false,"isOut":false,"name":"radius","tag":"Parameter","type":{"kind":"Prim","name":"Float","tag":"Type"}}],"returnType":null,"source":"cyberpunk/UI/hud/cyberwareBreach/cyberwareBreachGameController.script","tag":"Function","visibility":"private"},{"isCallback":false,"isExec":false,"isFinal":true,"isNative":false,"isStatic":false,"name":"ChangeHealth;FloatFloatBool","parameters":[{"isOptional":false,"isOut":false,"name":"health","tag":"Parameter","type":{"kind":"Prim","name":"Float","tag":"Type"}},{"isOptional":false,"isOut":false,"name":"givenMaxHealth","tag":"Parameter","type":{"kind":"Prim","name":"Float","tag":"Type"}},{"isOptional":true,"isOut":false,"name":"fireTransition","tag":"Parameter","type":{"kind":"Prim","name":"Bool","tag":"Type"}}],"returnType":null,"source":"cyberpunk/UI/hud/cyberwareBreach/cyberwareBreachGameController.script","tag":"Function","visibility":"private"},{"isCallback":false,"isExec":false,"isFinal":true,"isNative":false,"isStatic":false,"name":"ChangeFluff;Vector2Float","parameters":[{"isOptional":false,"isOut":false,"name":"screenPosition","tag":"Parameter","type":{"index":22278,"kind":"Class","name":"Vector2","tag":"Type"}},{"isOptional":false,"isOut":false,"name":"radius","tag":"Parameter","type":{"kind":"Prim","name":"Float","tag":"Type"}}],"returnType":null,"source":"cyberpunk/UI/hud/cyberwareBreach/cyberwareBreachGameController.script","tag":"Function","visibility":"private"},{"isCallback":false,"isExec":false,"isFinal":true,"isNative":false,"isStatic":false,"name":"InterpolateValues;FloatFloatFloat","parameters":[{"isOptional":false,"isOut":false,"name":"startValue","tag":"Parameter","type":{"kind":"Prim","name":"Float","tag":"Type"}},{"isOptional":false,"isOut":false,"name":"endValue","tag":"Parameter","type":{"kind":"Prim","name":"Float","tag":"Type"}},{"isOptional":false,"isOut":false,"name":"ratio","tag":"Parameter","type":{"kind":"Prim","name":"Float","tag":"Type"}}],"returnType":{"kind":"Prim","name":"Float","tag":"Type"},"source":"cyberpunk/UI/hud/cyberwareBreach/cyberwareBreachGameController.script","tag":"Function","visibility":"private"},{"isCallback":false,"isExec":false,"isFinal":true,"isNative":false,"isStatic":false,"name":"IsAnyIntroAnimPlaying;Bool","parameters":[{"isOptional":false,"isOut":false,"name":"ignoreSizeAnim","tag":"Parameter","type":{"kind":"Prim","name":"Bool","tag":"Type"}}],"returnType":{"kind":"Prim","name":"Bool","tag":"Type"},"source":"cyberpunk/UI/hud/cyberwareBreach/cyberwareBreachGameController.script","tag":"Function","visibility":"private"},{"isCallback":false,"isExec":false,"isFinal":true,"isNative":false,"isStatic":false,"name":"PlayIntroAnimation;","parameters":[],"returnType":null,"source":"cyberpunk/UI/hud/cyberwareBreach/cyberwareBreachGameController.script","tag":"Function","visibility":"private"},{"isCallback":true,"isExec":false,"isFinal":false,"isNative":false,"isStatic":false,"name":"OnIntroAnimationFinished","parameters":[{"isOptional":false,"isOut":false,"name":"proxy","tag":"Parameter","type":{"inner":{"index":54304,"kind":"Class","name":"inkAnimProxy","tag":"Type"},"kind":"Ref","tag":"Type"}}],"returnType":{"kind":"Prim","name":"Bool","tag":"Type"},"source":"cyberpunk/UI/hud/cyberwareBreach/cyberwareBreachGameController.script","tag":"Function","visibility":"protected"},{"isCallback":false,"isExec":false,"isFinal":true,"isNative":false,"isStatic":false,"name":"PlayShowAnimation;","parameters":[],"returnType":null,"source":"cyberpunk/UI/hud/cyberwareBreach/cyberwareBreachGameController.script","tag":"Function","visibility":"private"},{"isCallback":true,"isExec":false,"isFinal":false,"isNative":false,"isStatic":false,"name":"OnShowAnimationFinished","parameters":[{"isOptional":false,"isOut":false,"name":"proxy","tag":"Parameter","type":{"inner":{"index":54304,"kind":"Class","name":"inkAnimProxy","tag":"Type"},"kind":"Ref","tag":"Type"}}],"returnType":{"kind":"Prim","name":"Bool","tag":"Type"},"source":"cyberpunk/UI/hud/cyberwareBreach/cyberwareBreachGameController.script","tag":"Function","visibility":"protected"},{"isCallback":false,"isExec":false,"isFinal":true,"isNative":false,"isStatic":false,"name":"PlayTimeoutAnimation;","parameters":[],"returnType":null,"source":"cyberpunk/UI/hud/cyberwareBreach/cyberwareBreachGameController.script","tag":"Function","visibility":"private"},{"isCallback":false,"isExec":false,"isFinal":true,"isNative":false,"isStatic":false,"name":"StopAllAnimations;","parameters":[],"returnType":null,"source":"cyberpunk/UI/hud/cyberwareBreach/cyberwareBreachGameController.script","tag":"Function","visibility":"private"},{"isCallback":true,"isExec":false,"isFinal":false,"isNative":false,"isStatic":false,"name":"OnMoveAnimationFinished","parameters":[],"returnType":{"kind":"Prim","name":"Bool","tag":"Type"},"source":"cyberpunk/UI/hud/cyberwareBreach/cyberwareBreachGameController.script","tag":"Function","visibility":"protected"},{"isCallback":true,"isExec":false,"isFinal":false,"isNative":false,"isStatic":false,"name":"OnResizeAnimationFinished","parameters":[],"returnType":{"kind":"Prim","name":"Bool","tag":"Type"},"source":"cyberpunk/UI/hud/cyberwareBreach/cyberwareBreachGameController.script","tag":"Function","visibility":"protected"}],"name":"gameaiCyberwareBreachGameController","tag":"Class","visibility":"public"}