{"bases":[{"base":null,"index":27301,"name":"WeaponObject"},{"base":null,"index":21749,"name":"ItemObject"},{"base":null,"index":10101,"name":"TimeDilatable"},{"base":null,"index":9469,"name":"GameObject"},{"base":null,"index":9468,"name":"GameEntity"},{"base":null,"index":9329,"name":"Entity"},{"base":null,"index":9314,"name":"IScriptable"}],"fields":[{"isConst":false,"isEdit":false,"isInline":false,"isNative":false,"isPersistent":false,"isRep":false,"name":"m_colliderComponent","tag":"Field","type":{"inner":{"index":15003,"kind":"Class","name":"IComponent","tag":"Type"},"kind":"Ref","tag":"Type"}},{"isConst":false,"isEdit":true,"isInline":false,"isNative":false,"isPersistent":false,"isRep":false,"name":"m_gameEffectRef","tag":"Field","type":{"index":102351,"kind":"Class","name":"EffectRef","tag":"Type"}},{"isConst":false,"isEdit":false,"isInline":false,"isNative":false,"isPersistent":false,"isRep":false,"name":"gameEffectInstance","tag":"Field","type":{"inner":{"index":21922,"kind":"Class","name":"EffectInstance","tag":"Type"},"kind":"Ref","tag":"Type"}},{"isConst":false,"isEdit":false,"isInline":false,"isNative":false,"isPersistent":false,"isRep":false,"name":"jammedSensorsArray","tag":"Field","type":{"inner":{"inner":{"index":33749,"kind":"Class","name":"SensorDevice","tag":"Type"},"kind":"WeakRef","tag":"Type"},"kind":"Array","tag":"Type"}}],"isAbstract":false,"isFinal":false,"isNative":false,"isStruct":false,"methods":[{"isCallback":true,"isExec":false,"isFinal":false,"isNative":false,"isStatic":false,"name":"OnRequestComponents","parameters":[{"isOptional":false,"isOut":false,"name":"ri","tag":"Parameter","type":{"index":17383,"kind":"Class","name":"EntityRequestComponentsInterface","tag":"Type"}}],"returnType":{"kind":"Prim","name":"Bool","tag":"Type"},"source":"cyberpunk/items/antiRadar.script","tag":"Function","visibility":"protected"},{"isCallback":true,"isExec":false,"isFinal":false,"isNative":false,"isStatic":false,"name":"OnTakeControl","parameters":[{"isOptional":false,"isOut":false,"name":"ri","tag":"Parameter","type":{"index":23654,"kind":"Class","name":"EntityResolveComponentsInterface","tag":"Type"}}],"returnType":{"kind":"Prim","name":"Bool","tag":"Type"},"source":"cyberpunk/items/antiRadar.script","tag":"Function","visibility":"protected"},{"isCallback":true,"isExec":false,"isFinal":false,"isNative":false,"isStatic":false,"name":"OnChargeStartedEvent","parameters":[{"isOptional":false,"isOut":false,"name":"evt","tag":"Parameter","type":{"inner":{"index":152350,"kind":"Class","name":"ChargeStartedEvent","tag":"Type"},"kind":"Ref","tag":"Type"}}],"returnType":{"kind":"Prim","name":"Bool","tag":"Type"},"source":"cyberpunk/items/antiRadar.script","tag":"Function","visibility":"protected"},{"isCallback":true,"isExec":false,"isFinal":false,"isNative":false,"isStatic":false,"name":"OnChargeEndedEvent","parameters":[{"isOptional":false,"isOut":false,"name":"evt","tag":"Parameter","type":{"inner":{"index":152355,"kind":"Class","name":"ChargeEndedEvent","tag":"Type"},"kind":"Ref","tag":"Type"}}],"returnType":{"kind":"Prim","name":"Bool","tag":"Type"},"source":"cyberpunk/items/antiRadar.script","tag":"Function","visibility":"protected"},{"isCallback":true,"isExec":false,"isFinal":false,"isNative":false,"isStatic":false,"name":"OnSensorJammed","parameters":[{"isOptional":false,"isOut":false,"name":"evt","tag":"Parameter","type":{"inner":{"index":142407,"kind":"Class","name":"SensorJammed","tag":"Type"},"kind":"Ref","tag":"Type"}}],"returnType":{"kind":"Prim","name":"Bool","tag":"Type"},"source":"cyberpunk/items/antiRadar.script","tag":"Function","visibility":"protected"},{"isCallback":false,"isExec":false,"isFinal":true,"isNative":false,"isStatic":false,"name":"ChangeAppearance;CName","parameters":[{"isOptional":false,"isOut":false,"name":"newAppearance","tag":"Parameter","type":{"kind":"Prim","name":"CName","tag":"Type"}}],"returnType":null,"source":"cyberpunk/items/antiRadar.script","tag":"Function","visibility":"protected"}],"name":"AntiRadar","tag":"Class","visibility":"public"}