{"bases":[{"base":null,"index":54403,"name":"inkLogicController"},{"base":null,"index":22196,"name":"inkILogicController"},{"base":null,"index":11333,"name":"IScriptable"}],"fields":[{"isConst":false,"isEdit":false,"isInline":false,"isNative":false,"isPersistent":false,"isRep":false,"name":"offsetLeftRight","tag":"Field","type":{"kind":"Prim","name":"Float","tag":"Type"}},{"isConst":false,"isEdit":false,"isInline":false,"isNative":false,"isPersistent":false,"isRep":false,"name":"latchVertical","tag":"Field","type":{"kind":"Prim","name":"Float","tag":"Type"}},{"isConst":false,"isEdit":true,"isInline":false,"isNative":false,"isPersistent":false,"isRep":false,"name":"m_topPart","tag":"Field","type":{"index":54543,"kind":"Class","name":"inkWidgetRef","tag":"Type"}},{"isConst":false,"isEdit":true,"isInline":false,"isNative":false,"isPersistent":false,"isRep":false,"name":"m_bottomPart","tag":"Field","type":{"index":54543,"kind":"Class","name":"inkWidgetRef","tag":"Type"}},{"isConst":false,"isEdit":true,"isInline":false,"isNative":false,"isPersistent":false,"isRep":false,"name":"m_horiPart","tag":"Field","type":{"index":54543,"kind":"Class","name":"inkWidgetRef","tag":"Type"}},{"isConst":false,"isEdit":true,"isInline":false,"isNative":false,"isPersistent":false,"isRep":false,"name":"m_vertPart","tag":"Field","type":{"index":54543,"kind":"Class","name":"inkWidgetRef","tag":"Type"}},{"isConst":false,"isEdit":true,"isInline":false,"isNative":false,"isPersistent":false,"isRep":false,"name":"m_leftPart","tag":"Field","type":{"index":54543,"kind":"Class","name":"inkWidgetRef","tag":"Type"}},{"isConst":false,"isEdit":true,"isInline":false,"isNative":false,"isPersistent":false,"isRep":false,"name":"m_rightPart","tag":"Field","type":{"index":54543,"kind":"Class","name":"inkWidgetRef","tag":"Type"}},{"isConst":false,"isEdit":true,"isInline":false,"isNative":false,"isPersistent":false,"isRep":false,"name":"m_targetColorChange","tag":"Field","type":{"index":54543,"kind":"Class","name":"inkWidgetRef","tag":"Type"}}],"isAbstract":false,"isFinal":false,"isNative":false,"isStruct":false,"methods":[{"isCallback":false,"isExec":false,"isFinal":true,"isNative":false,"isStatic":false,"name":"ApplyBulletSpread;Vector2","parameters":[{"isOptional":false,"isOut":false,"name":"spread","tag":"Parameter","type":{"index":22278,"kind":"Class","name":"Vector2","tag":"Type"}}],"returnType":null,"source":"cyberpunk/UI/weapons/crosshairs/crosshairController_Rasetsu.script","tag":"Function","visibility":"public"},{"isCallback":false,"isExec":false,"isFinal":true,"isNative":false,"isStatic":false,"name":"ApplyCrosshairGUIState;CNameEntity","parameters":[{"isOptional":false,"isOut":false,"name":"state","tag":"Parameter","type":{"kind":"Prim","name":"CName","tag":"Type"}},{"isOptional":false,"isOut":false,"name":"aimedAtEntity","tag":"Parameter","type":{"inner":{"index":11340,"kind":"Class","name":"Entity","tag":"Type"},"kind":"Ref","tag":"Type"}}],"returnType":null,"source":"cyberpunk/UI/weapons/crosshairs/crosshairController_Rasetsu.script","tag":"Function","visibility":"public"}],"name":"CrosshairLogicController_RasetsuHipFire","tag":"Class","visibility":"public"}