{"bases":[{"base":null,"index":11333,"name":"IScriptable"}],"fields":[{"isConst":false,"isEdit":false,"isInline":false,"isNative":false,"isPersistent":false,"isRep":false,"name":"m_gameInstance","tag":"Field","type":{"index":11560,"kind":"Class","name":"GameInstance","tag":"Type"}},{"isConst":false,"isEdit":false,"isInline":false,"isNative":false,"isPersistent":false,"isRep":false,"name":"m_vendorObject","tag":"Field","type":{"inner":{"index":11500,"kind":"Class","name":"GameObject","tag":"Type"},"kind":"WeakRef","tag":"Type"}},{"isConst":false,"isEdit":false,"isInline":false,"isNative":false,"isPersistent":true,"isRep":false,"name":"m_tweakID","tag":"Field","type":{"kind":"Prim","name":"TweakDBID","tag":"Type"}},{"isConst":false,"isEdit":false,"isInline":false,"isNative":false,"isPersistent":true,"isRep":false,"name":"m_lastInteractionTime","tag":"Field","type":{"kind":"Prim","name":"Float","tag":"Type"}},{"isConst":false,"isEdit":false,"isInline":false,"isNative":false,"isPersistent":true,"isRep":false,"name":"m_stock","tag":"Field","type":{"inner":{"index":25061,"kind":"Class","name":"SItemStack","tag":"Type"},"kind":"Array","tag":"Type"}},{"isConst":false,"isEdit":false,"isInline":false,"isNative":false,"isPersistent":true,"isRep":false,"name":"m_newItems","tag":"Field","type":{"inner":{"kind":"Prim","name":"TweakDBID","tag":"Type"},"kind":"Array","tag":"Type"}},{"isConst":false,"isEdit":false,"isInline":false,"isNative":false,"isPersistent":true,"isRep":false,"name":"m_soldItems","tag":"Field","type":{"inner":{"index":24995,"kind":"Class","name":"SoldItemsCache","tag":"Type"},"kind":"Ref","tag":"Type"}},{"isConst":false,"isEdit":false,"isInline":false,"isNative":false,"isPersistent":true,"isRep":false,"name":"m_priceMultiplier","tag":"Field","type":{"kind":"Prim","name":"Float","tag":"Type"}},{"isConst":false,"isEdit":false,"isInline":false,"isNative":false,"isPersistent":true,"isRep":false,"name":"m_vendorPersistentID","tag":"Field","type":{"index":18092,"kind":"Class","name":"PersistentID","tag":"Type"}},{"isConst":false,"isEdit":false,"isInline":false,"isNative":false,"isPersistent":false,"isRep":false,"name":"m_stockInit","tag":"Field","type":{"kind":"Prim","name":"Bool","tag":"Type"}},{"isConst":false,"isEdit":false,"isInline":false,"isNative":false,"isPersistent":false,"isRep":false,"name":"m_playerHacksInit","tag":"Field","type":{"kind":"Prim","name":"Bool","tag":"Type"}},{"isConst":false,"isEdit":false,"isInline":false,"isNative":false,"isPersistent":false,"isRep":false,"name":"m_inventoryInit","tag":"Field","type":{"kind":"Prim","name":"Bool","tag":"Type"}},{"isConst":false,"isEdit":false,"isInline":false,"isNative":false,"isPersistent":false,"isRep":false,"name":"m_isAttached","tag":"Field","type":{"kind":"Prim","name":"Bool","tag":"Type"}},{"isConst":false,"isEdit":false,"isInline":false,"isNative":false,"isPersistent":false,"isRep":false,"name":"m_inventoryReinitWithPlayerStats","tag":"Field","type":{"kind":"Prim","name":"Bool","tag":"Type"}},{"isConst":false,"isEdit":false,"isInline":false,"isNative":false,"isPersistent":false,"isRep":false,"name":"m_vendorRecord","tag":"Field","type":{"inner":{"index":24861,"kind":"Class","name":"Vendor_Record","tag":"Type"},"kind":"WeakRef","tag":"Type"}},{"isConst":false,"isEdit":false,"isInline":false,"isNative":false,"isPersistent":false,"isRep":false,"name":"m_playerHacks","tag":"Field","type":{"inner":{"index":21838,"kind":"Class","name":"ItemID","tag":"Type"},"kind":"Array","tag":"Type"}}],"isAbstract":false,"isFinal":false,"isNative":false,"isStruct":false,"methods":[{"isCallback":false,"isExec":false,"isFinal":true,"isNative":false,"isStatic":true,"name":"ShouldDiscardQualityForNewCWs;","parameters":[],"returnType":{"kind":"Prim","name":"Bool","tag":"Type"},"source":"cyberpunk/systems/marketSystem/vendor.script","tag":"Function","visibility":"private"},{"isCallback":false,"isExec":false,"isFinal":true,"isNative":false,"isStatic":false,"name":"Initialize;GameInstanceTweakDBIDGameObject","parameters":[{"isOptional":false,"isOut":false,"name":"gameInstance","tag":"Parameter","type":{"index":11560,"kind":"Class","name":"GameInstance","tag":"Type"}},{"isOptional":false,"isOut":false,"name":"vendorID","tag":"Parameter","type":{"kind":"Prim","name":"TweakDBID","tag":"Type"}},{"isOptional":false,"isOut":false,"name":"vendorObject","tag":"Parameter","type":{"inner":{"index":11500,"kind":"Class","name":"GameObject","tag":"Type"},"kind":"Ref","tag":"Type"}}],"returnType":null,"source":"cyberpunk/systems/marketSystem/vendor.script","tag":"Function","visibility":"public"},{"isCallback":false,"isExec":false,"isFinal":true,"isNative":false,"isStatic":false,"name":"OnAttach;GameObject","parameters":[{"isOptional":false,"isOut":false,"name":"owner","tag":"Parameter","type":{"inner":{"index":11500,"kind":"Class","name":"GameObject","tag":"Type"},"kind":"WeakRef","tag":"Type"}}],"returnType":null,"source":"cyberpunk/systems/marketSystem/vendor.script","tag":"Function","visibility":"public"},{"isCallback":false,"isExec":false,"isFinal":true,"isNative":false,"isStatic":false,"name":"OnDeattach;GameObject","parameters":[{"isOptional":false,"isOut":false,"name":"owner","tag":"Parameter","type":{"inner":{"index":11500,"kind":"Class","name":"GameObject","tag":"Type"},"kind":"WeakRef","tag":"Type"}}],"returnType":null,"source":"cyberpunk/systems/marketSystem/vendor.script","tag":"Function","visibility":"public"},{"isCallback":false,"isExec":false,"isFinal":true,"isNative":false,"isStatic":false,"name":"OnRestored;GameInstanceBool","parameters":[{"isOptional":false,"isOut":false,"name":"gameInstance","tag":"Parameter","type":{"index":11560,"kind":"Class","name":"GameInstance","tag":"Type"}},{"isOptional":false,"isOut":false,"name":"forceReinit","tag":"Parameter","type":{"kind":"Prim","name":"Bool","tag":"Type"}}],"returnType":null,"source":"cyberpunk/systems/marketSystem/vendor.script","tag":"Function","visibility":"public"},{"isCallback":false,"isExec":false,"isFinal":true,"isNative":false,"isStatic":false,"name":"IsAttached;","parameters":[],"returnType":{"kind":"Prim","name":"Bool","tag":"Type"},"source":"cyberpunk/systems/marketSystem/vendor.script","tag":"Function","visibility":"public"},{"isCallback":false,"isExec":false,"isFinal":true,"isNative":false,"isStatic":false,"name":"GetStock;","parameters":[],"returnType":{"inner":{"index":25061,"kind":"Class","name":"SItemStack","tag":"Type"},"kind":"Array","tag":"Type"},"source":"cyberpunk/systems/marketSystem/vendor.script","tag":"Function","visibility":"public"},{"isCallback":false,"isExec":false,"isFinal":true,"isNative":false,"isStatic":false,"name":"LazyInitStock;","parameters":[],"returnType":null,"source":"cyberpunk/systems/marketSystem/vendor.script","tag":"Function","visibility":"private"},{"isCallback":false,"isExec":false,"isFinal":true,"isNative":false,"isStatic":false,"name":"InitPlayerHacks;","parameters":[],"returnType":null,"source":"cyberpunk/systems/marketSystem/vendor.script","tag":"Function","visibility":"private"},{"isCallback":false,"isExec":false,"isFinal":true,"isNative":false,"isStatic":true,"name":"GetMaxItemStacksPerVendor;Bool","parameters":[{"isOptional":true,"isOut":false,"name":"useIncreasedLimit","tag":"Parameter","type":{"kind":"Prim","name":"Bool","tag":"Type"}}],"returnType":{"kind":"Prim","name":"Int32","tag":"Type"},"source":"cyberpunk/systems/marketSystem/vendor.script","tag":"Function","visibility":"public"},{"isCallback":false,"isExec":false,"isFinal":true,"isNative":false,"isStatic":false,"name":"GetVendorPersistentID;","parameters":[],"returnType":{"index":18092,"kind":"Class","name":"PersistentID","tag":"Type"},"source":"cyberpunk/systems/marketSystem/vendor.script","tag":"Function","visibility":"public"},{"isCallback":false,"isExec":false,"isFinal":true,"isNative":false,"isStatic":false,"name":"GetVendorTweakID;","parameters":[],"returnType":{"kind":"Prim","name":"TweakDBID","tag":"Type"},"source":"cyberpunk/systems/marketSystem/vendor.script","tag":"Function","visibility":"public"},{"isCallback":false,"isExec":false,"isFinal":true,"isNative":false,"isStatic":false,"name":"GetVendorType;","parameters":[],"returnType":{"index":7305,"kind":"Class","name":"gamedataVendorType","tag":"Type"},"source":"cyberpunk/systems/marketSystem/vendor.script","tag":"Function","visibility":"public"},{"isCallback":false,"isExec":false,"isFinal":true,"isNative":false,"isStatic":false,"name":"GetVendorRecord;","parameters":[],"returnType":{"inner":{"index":24861,"kind":"Class","name":"Vendor_Record","tag":"Type"},"kind":"Ref","tag":"Type"},"source":"cyberpunk/systems/marketSystem/vendor.script","tag":"Function","visibility":"public"},{"isCallback":false,"isExec":false,"isFinal":true,"isNative":false,"isStatic":false,"name":"GetVendorObject;","parameters":[],"returnType":{"inner":{"index":11500,"kind":"Class","name":"GameObject","tag":"Type"},"kind":"WeakRef","tag":"Type"},"source":"cyberpunk/systems/marketSystem/vendor.script","tag":"Function","visibility":"public"},{"isCallback":false,"isExec":false,"isFinal":true,"isNative":false,"isStatic":false,"name":"GetPriceMultiplier;","parameters":[],"returnType":{"kind":"Prim","name":"Float","tag":"Type"},"source":"cyberpunk/systems/marketSystem/vendor.script","tag":"Function","visibility":"public"},{"isCallback":false,"isExec":false,"isFinal":true,"isNative":false,"isStatic":false,"name":"GetLastInteractionTime;","parameters":[],"returnType":{"kind":"Prim","name":"Float","tag":"Type"},"source":"cyberpunk/systems/marketSystem/vendor.script","tag":"Function","visibility":"public"},{"isCallback":false,"isExec":false,"isFinal":true,"isNative":false,"isStatic":false,"name":"GetSoldItems;","parameters":[],"returnType":{"inner":{"index":24995,"kind":"Class","name":"SoldItemsCache","tag":"Type"},"kind":"Ref","tag":"Type"},"source":"cyberpunk/systems/marketSystem/vendor.script","tag":"Function","visibility":"public"},{"isCallback":false,"isExec":false,"isFinal":true,"isNative":false,"isStatic":false,"name":"GetItemsForSale;Bool","parameters":[{"isOptional":false,"isOut":false,"name":"checkPlayerCanBuy","tag":"Parameter","type":{"kind":"Prim","name":"Bool","tag":"Type"}}],"returnType":{"inner":{"index":25061,"kind":"Class","name":"SItemStack","tag":"Type"},"kind":"Array","tag":"Type"},"source":"cyberpunk/systems/marketSystem/vendor.script","tag":"Function","visibility":"public"},{"isCallback":false,"isExec":false,"isFinal":true,"isNative":false,"isStatic":false,"name":"GetMoney;","parameters":[],"returnType":{"kind":"Prim","name":"Int32","tag":"Type"},"source":"cyberpunk/systems/marketSystem/vendor.script","tag":"Function","visibility":"public"},{"isCallback":false,"isExec":false,"isFinal":true,"isNative":false,"isStatic":false,"name":"GetCyberwareForSale;Bool","parameters":[{"isOptional":false,"isOut":false,"name":"checkPlayerCanBuy","tag":"Parameter","type":{"kind":"Prim","name":"Bool","tag":"Type"}}],"returnType":{"inner":{"index":25061,"kind":"Class","name":"SItemStack","tag":"Type"},"kind":"Array","tag":"Type"},"source":"cyberpunk/systems/marketSystem/vendor.script","tag":"Function","visibility":"public"},{"isCallback":false,"isExec":false,"isFinal":true,"isNative":false,"isStatic":false,"name":"GetAllStockForSale;Bool","parameters":[{"isOptional":false,"isOut":false,"name":"checkPlayerCanBuy","tag":"Parameter","type":{"kind":"Prim","name":"Bool","tag":"Type"}}],"returnType":{"inner":{"index":25061,"kind":"Class","name":"SItemStack","tag":"Type"},"kind":"Array","tag":"Type"},"source":"cyberpunk/systems/marketSystem/vendor.script","tag":"Function","visibility":"public"},{"isCallback":false,"isExec":false,"isFinal":true,"isNative":false,"isStatic":false,"name":"GetItemsPlayerCanSell;BoolBool","parameters":[{"isOptional":false,"isOut":false,"name":"allowQuestItems","tag":"Parameter","type":{"kind":"Prim","name":"Bool","tag":"Type"}},{"isOptional":false,"isOut":false,"name":"excludeEquipped","tag":"Parameter","type":{"kind":"Prim","name":"Bool","tag":"Type"}}],"returnType":{"inner":{"index":25061,"kind":"Class","name":"SItemStack","tag":"Type"},"kind":"Array","tag":"Type"},"source":"cyberpunk/systems/marketSystem/vendor.script","tag":"Function","visibility":"public"},{"isCallback":false,"isExec":false,"isFinal":true,"isNative":false,"isStatic":false,"name":"OnVendorMenuOpen;","parameters":[],"returnType":null,"source":"cyberpunk/systems/marketSystem/vendor.script","tag":"Function","visibility":"public"},{"isCallback":false,"isExec":false,"isFinal":true,"isNative":false,"isStatic":false,"name":"SetPriceMultiplier;Float","parameters":[{"isOptional":false,"isOut":false,"name":"value","tag":"Parameter","type":{"kind":"Prim","name":"Float","tag":"Type"}}],"returnType":null,"source":"cyberpunk/systems/marketSystem/vendor.script","tag":"Function","visibility":"public"},{"isCallback":false,"isExec":false,"isFinal":true,"isNative":false,"isStatic":false,"name":"SetPersistentID;PersistentID","parameters":[{"isOptional":false,"isOut":false,"name":"persistentID","tag":"Parameter","type":{"index":18092,"kind":"Class","name":"PersistentID","tag":"Type"}}],"returnType":null,"source":"cyberpunk/systems/marketSystem/vendor.script","tag":"Function","visibility":"public"},{"isCallback":false,"isExec":false,"isFinal":true,"isNative":false,"isStatic":false,"name":"PlayerCanSell;ItemIDBoolBool","parameters":[{"isOptional":false,"isOut":false,"name":"itemID","tag":"Parameter","type":{"index":21838,"kind":"Class","name":"ItemID","tag":"Type"}},{"isOptional":false,"isOut":false,"name":"allowQuestItems","tag":"Parameter","type":{"kind":"Prim","name":"Bool","tag":"Type"}},{"isOptional":false,"isOut":false,"name":"excludeEquipped","tag":"Parameter","type":{"kind":"Prim","name":"Bool","tag":"Type"}}],"returnType":{"kind":"Prim","name":"Bool","tag":"Type"},"source":"cyberpunk/systems/marketSystem/vendor.script","tag":"Function","visibility":"public"},{"isCallback":false,"isExec":false,"isFinal":true,"isNative":false,"isStatic":false,"name":"PlayerCanBuy;script_ref<SItemStack>","parameters":[{"isOptional":false,"isOut":false,"name":"itemStack","tag":"Parameter","type":{"inner":{"index":25061,"kind":"Class","name":"SItemStack","tag":"Type"},"kind":"ScriptRef","tag":"Type"}}],"returnType":{"kind":"Prim","name":"Bool","tag":"Type"},"source":"cyberpunk/systems/marketSystem/vendor.script","tag":"Function","visibility":"private"},{"isCallback":false,"isExec":false,"isFinal":true,"isNative":false,"isStatic":false,"name":"CompareWithPlayerGrenadesQuality;script_ref<SItemStack>","parameters":[{"isOptional":false,"isOut":false,"name":"itemStack","tag":"Parameter","type":{"inner":{"index":25061,"kind":"Class","name":"SItemStack","tag":"Type"},"kind":"ScriptRef","tag":"Type"}}],"returnType":{"kind":"Prim","name":"Bool","tag":"Type"},"source":"cyberpunk/systems/marketSystem/vendor.script","tag":"Function","visibility":"private"},{"isCallback":false,"isExec":false,"isFinal":true,"isNative":false,"isStatic":false,"name":"CompareWithPlayerHealingItemsQuality;script_ref<SItemStack>","parameters":[{"isOptional":false,"isOut":false,"name":"itemStack","tag":"Parameter","type":{"inner":{"index":25061,"kind":"Class","name":"SItemStack","tag":"Type"},"kind":"ScriptRef","tag":"Type"}}],"returnType":{"kind":"Prim","name":"Bool","tag":"Type"},"source":"cyberpunk/systems/marketSystem/vendor.script","tag":"Function","visibility":"private"},{"isCallback":false,"isExec":false,"isFinal":true,"isNative":false,"isStatic":false,"name":"FillVendorInventory;Bool","parameters":[{"isOptional":false,"isOut":false,"name":"allowRegeneration","tag":"Parameter","type":{"kind":"Prim","name":"Bool","tag":"Type"}}],"returnType":null,"source":"cyberpunk/systems/marketSystem/vendor.script","tag":"Function","visibility":"private"},{"isCallback":false,"isExec":false,"isFinal":true,"isNative":false,"isStatic":false,"name":"InitializeStock;","parameters":[],"returnType":null,"source":"cyberpunk/systems/marketSystem/vendor.script","tag":"Function","visibility":"private"},{"isCallback":false,"isExec":false,"isFinal":true,"isNative":false,"isStatic":false,"name":"LoadPlayerHacks;","parameters":[],"returnType":null,"source":"cyberpunk/systems/marketSystem/vendor.script","tag":"Function","visibility":"private"},{"isCallback":false,"isExec":false,"isFinal":true,"isNative":false,"isStatic":false,"name":"RegenerateStock;","parameters":[],"returnType":null,"source":"cyberpunk/systems/marketSystem/vendor.script","tag":"Function","visibility":"private"},{"isCallback":false,"isExec":false,"isFinal":true,"isNative":false,"isStatic":false,"name":"UpdateNewItems;script_ref<array<SItemStack>>","parameters":[{"isOptional":false,"isOut":false,"name":"newStock","tag":"Parameter","type":{"inner":{"inner":{"index":25061,"kind":"Class","name":"SItemStack","tag":"Type"},"kind":"Array","tag":"Type"},"kind":"ScriptRef","tag":"Type"}}],"returnType":null,"source":"cyberpunk/systems/marketSystem/vendor.script","tag":"Function","visibility":"private"},{"isCallback":false,"isExec":false,"isFinal":true,"isNative":false,"isStatic":false,"name":"CalculateQuantityForStack;VendorWare_RecordPlayerPuppet","parameters":[{"isOptional":false,"isOut":false,"name":"vendorWare","tag":"Parameter","type":{"inner":{"index":17694,"kind":"Class","name":"VendorWare_Record","tag":"Type"},"kind":"Ref","tag":"Type"}},{"isOptional":false,"isOut":false,"name":"player","tag":"Parameter","type":{"inner":{"index":18946,"kind":"Class","name":"PlayerPuppet","tag":"Type"},"kind":"Ref","tag":"Type"}}],"returnType":{"kind":"Prim","name":"Int32","tag":"Type"},"source":"cyberpunk/systems/marketSystem/vendor.script","tag":"Function","visibility":"private"},{"isCallback":false,"isExec":false,"isFinal":true,"isNative":false,"isStatic":false,"name":"InitSingleItemStack;SItemStackItem_RecordItemID","parameters":[{"isOptional":false,"isOut":true,"name":"itemStack","tag":"Parameter","type":{"index":25061,"kind":"Class","name":"SItemStack","tag":"Type"}},{"isOptional":false,"isOut":false,"name":"itemRecord","tag":"Parameter","type":{"inner":{"index":14347,"kind":"Class","name":"Item_Record","tag":"Type"},"kind":"Ref","tag":"Type"}},{"isOptional":false,"isOut":false,"name":"itemID","tag":"Parameter","type":{"index":21838,"kind":"Class","name":"ItemID","tag":"Type"}}],"returnType":null,"source":"cyberpunk/systems/marketSystem/vendor.script","tag":"Function","visibility":"private"},{"isCallback":false,"isExec":false,"isFinal":true,"isNative":false,"isStatic":false,"name":"CreateStacksFromVendorItemQuery;array<SItemStack>VendorItemQuery_RecordPlayerPuppet","parameters":[{"isOptional":false,"isOut":true,"name":"outputStack","tag":"Parameter","type":{"inner":{"index":25061,"kind":"Class","name":"SItemStack","tag":"Type"},"kind":"Array","tag":"Type"}},{"isOptional":false,"isOut":false,"name":"vendorItemQuery","tag":"Parameter","type":{"inner":{"index":25170,"kind":"Class","name":"VendorItemQuery_Record","tag":"Type"},"kind":"WeakRef","tag":"Type"}},{"isOptional":false,"isOut":false,"name":"player","tag":"Parameter","type":{"inner":{"index":18946,"kind":"Class","name":"PlayerPuppet","tag":"Type"},"kind":"Ref","tag":"Type"}}],"returnType":null,"source":"cyberpunk/systems/marketSystem/vendor.script","tag":"Function","visibility":"private"},{"isCallback":false,"isExec":false,"isFinal":true,"isNative":false,"isStatic":false,"name":"CreateStacksFromVendorItem;array<SItemStack>VendorItem_RecordPlayerPuppet","parameters":[{"isOptional":false,"isOut":true,"name":"outputStacks","tag":"Parameter","type":{"inner":{"index":25061,"kind":"Class","name":"SItemStack","tag":"Type"},"kind":"Array","tag":"Type"}},{"isOptional":false,"isOut":false,"name":"vendorItem","tag":"Parameter","type":{"inner":{"index":25053,"kind":"Class","name":"VendorItem_Record","tag":"Type"},"kind":"WeakRef","tag":"Type"}},{"isOptional":false,"isOut":false,"name":"player","tag":"Parameter","type":{"inner":{"index":18946,"kind":"Class","name":"PlayerPuppet","tag":"Type"},"kind":"Ref","tag":"Type"}}],"returnType":null,"source":"cyberpunk/systems/marketSystem/vendor.script","tag":"Function","visibility":"private"},{"isCallback":false,"isExec":false,"isFinal":true,"isNative":false,"isStatic":false,"name":"CreateDynamicStockFromPlayerProgression;array<SItemStack>GameObject","parameters":[{"isOptional":false,"isOut":true,"name":"outputStacks","tag":"Parameter","type":{"inner":{"index":25061,"kind":"Class","name":"SItemStack","tag":"Type"},"kind":"Array","tag":"Type"}},{"isOptional":false,"isOut":false,"name":"player","tag":"Parameter","type":{"inner":{"index":11500,"kind":"Class","name":"GameObject","tag":"Type"},"kind":"WeakRef","tag":"Type"}}],"returnType":null,"source":"cyberpunk/systems/marketSystem/vendor.script","tag":"Function","visibility":"private"},{"isCallback":false,"isExec":false,"isFinal":false,"isNative":false,"isStatic":false,"name":"ShouldRegenerateStock;","parameters":[],"returnType":{"kind":"Prim","name":"Bool","tag":"Type"},"source":"cyberpunk/systems/marketSystem/vendor.script","tag":"Function","visibility":"protected"},{"isCallback":false,"isExec":false,"isFinal":true,"isNative":false,"isStatic":false,"name":"ShouldRegenerateItem;TweakDBID","parameters":[{"isOptional":false,"isOut":false,"name":"itemTDBID","tag":"Parameter","type":{"kind":"Prim","name":"TweakDBID","tag":"Type"}}],"returnType":{"kind":"Prim","name":"Bool","tag":"Type"},"source":"cyberpunk/systems/marketSystem/vendor.script","tag":"Function","visibility":"private"},{"isCallback":false,"isExec":false,"isFinal":true,"isNative":false,"isStatic":false,"name":"AlwaysInStock;TweakDBID","parameters":[{"isOptional":false,"isOut":false,"name":"itemTDBID","tag":"Parameter","type":{"kind":"Prim","name":"TweakDBID","tag":"Type"}}],"returnType":{"kind":"Prim","name":"Bool","tag":"Type"},"source":"cyberpunk/systems/marketSystem/vendor.script","tag":"Function","visibility":"private"},{"isCallback":false,"isExec":false,"isFinal":true,"isNative":false,"isStatic":false,"name":"SellItemToVendor;script_ref<SItemStack>Int32","parameters":[{"isOptional":false,"isOut":false,"name":"itemStack","tag":"Parameter","type":{"inner":{"index":25061,"kind":"Class","name":"SItemStack","tag":"Type"},"kind":"ScriptRef","tag":"Type"}},{"isOptional":false,"isOut":false,"name":"requestId","tag":"Parameter","type":{"kind":"Prim","name":"Int32","tag":"Type"}}],"returnType":null,"source":"cyberpunk/systems/marketSystem/vendor.script","tag":"Function","visibility":"public"},{"isCallback":false,"isExec":false,"isFinal":true,"isNative":false,"isStatic":false,"name":"SellItemsToVendor;script_ref<array<SItemStack>>Int32","parameters":[{"isOptional":false,"isOut":false,"name":"itemsStack","tag":"Parameter","type":{"inner":{"inner":{"index":25061,"kind":"Class","name":"SItemStack","tag":"Type"},"kind":"Array","tag":"Type"},"kind":"ScriptRef","tag":"Type"}},{"isOptional":false,"isOut":false,"name":"requestId","tag":"Parameter","type":{"kind":"Prim","name":"Int32","tag":"Type"}}],"returnType":null,"source":"cyberpunk/systems/marketSystem/vendor.script","tag":"Function","visibility":"public"},{"isCallback":false,"isExec":false,"isFinal":true,"isNative":false,"isStatic":false,"name":"BuyItemFromVendor;script_ref<SItemStack>Int32","parameters":[{"isOptional":false,"isOut":false,"name":"itemStack","tag":"Parameter","type":{"inner":{"index":25061,"kind":"Class","name":"SItemStack","tag":"Type"},"kind":"ScriptRef","tag":"Type"}},{"isOptional":false,"isOut":false,"name":"requestId","tag":"Parameter","type":{"kind":"Prim","name":"Int32","tag":"Type"}}],"returnType":null,"source":"cyberpunk/systems/marketSystem/vendor.script","tag":"Function","visibility":"public"},{"isCallback":false,"isExec":false,"isFinal":true,"isNative":false,"isStatic":false,"name":"BuyItemsFromVendor;script_ref<array<SItemStack>>Int32","parameters":[{"isOptional":false,"isOut":false,"name":"itemsStack","tag":"Parameter","type":{"inner":{"inner":{"index":25061,"kind":"Class","name":"SItemStack","tag":"Type"},"kind":"Array","tag":"Type"},"kind":"ScriptRef","tag":"Type"}},{"isOptional":false,"isOut":false,"name":"requestId","tag":"Parameter","type":{"kind":"Prim","name":"Int32","tag":"Type"}}],"returnType":null,"source":"cyberpunk/systems/marketSystem/vendor.script","tag":"Function","visibility":"public"},{"isCallback":false,"isExec":false,"isFinal":true,"isNative":false,"isStatic":false,"name":"BuybackItemFromVendor;script_ref<SItemStack>Int32","parameters":[{"isOptional":false,"isOut":false,"name":"itemStack","tag":"Parameter","type":{"inner":{"index":25061,"kind":"Class","name":"SItemStack","tag":"Type"},"kind":"ScriptRef","tag":"Type"}},{"isOptional":false,"isOut":false,"name":"requestId","tag":"Parameter","type":{"kind":"Prim","name":"Int32","tag":"Type"}}],"returnType":null,"source":"cyberpunk/systems/marketSystem/vendor.script","tag":"Function","visibility":"public"},{"isCallback":false,"isExec":false,"isFinal":true,"isNative":false,"isStatic":false,"name":"BuybackItemsFromVendor;script_ref<array<SItemStack>>Int32","parameters":[{"isOptional":false,"isOut":false,"name":"itemsStack","tag":"Parameter","type":{"inner":{"inner":{"index":25061,"kind":"Class","name":"SItemStack","tag":"Type"},"kind":"Array","tag":"Type"},"kind":"ScriptRef","tag":"Type"}},{"isOptional":false,"isOut":false,"name":"requestId","tag":"Parameter","type":{"kind":"Prim","name":"Int32","tag":"Type"}}],"returnType":null,"source":"cyberpunk/systems/marketSystem/vendor.script","tag":"Function","visibility":"public"},{"isCallback":false,"isExec":false,"isFinal":true,"isNative":false,"isStatic":false,"name":"DispenseItemFromVendor;Vector4ItemID","parameters":[{"isOptional":false,"isOut":false,"name":"position","tag":"Parameter","type":{"index":24588,"kind":"Class","name":"Vector4","tag":"Type"}},{"isOptional":true,"isOut":false,"name":"itemID","tag":"Parameter","type":{"index":21838,"kind":"Class","name":"ItemID","tag":"Type"}}],"returnType":null,"source":"cyberpunk/systems/marketSystem/vendor.script","tag":"Function","visibility":"public"},{"isCallback":false,"isExec":false,"isFinal":true,"isNative":false,"isStatic":false,"name":"DispenseItemStackFromVendor;Vector4ItemIDInt32Bool","parameters":[{"isOptional":false,"isOut":false,"name":"position","tag":"Parameter","type":{"index":24588,"kind":"Class","name":"Vector4","tag":"Type"}},{"isOptional":false,"isOut":false,"name":"itemID","tag":"Parameter","type":{"index":21838,"kind":"Class","name":"ItemID","tag":"Type"}},{"isOptional":false,"isOut":false,"name":"amount","tag":"Parameter","type":{"kind":"Prim","name":"Int32","tag":"Type"}},{"isOptional":true,"isOut":false,"name":"bypassStock","tag":"Parameter","type":{"kind":"Prim","name":"Bool","tag":"Type"}}],"returnType":null,"source":"cyberpunk/systems/marketSystem/vendor.script","tag":"Function","visibility":"public"},{"isCallback":false,"isExec":false,"isFinal":true,"isNative":false,"isStatic":false,"name":"GetRandomStockItem;","parameters":[],"returnType":{"index":21838,"kind":"Class","name":"ItemID","tag":"Type"},"source":"cyberpunk/systems/marketSystem/vendor.script","tag":"Function","visibility":"private"},{"isCallback":false,"isExec":false,"isFinal":true,"isNative":false,"isStatic":false,"name":"PerformItemTransfer;GameObjectGameObjectscript_ref<SItemTransaction>","parameters":[{"isOptional":false,"isOut":false,"name":"buyer","tag":"Parameter","type":{"inner":{"index":11500,"kind":"Class","name":"GameObject","tag":"Type"},"kind":"WeakRef","tag":"Type"}},{"isOptional":false,"isOut":false,"name":"seller","tag":"Parameter","type":{"inner":{"index":11500,"kind":"Class","name":"GameObject","tag":"Type"},"kind":"WeakRef","tag":"Type"}},{"isOptional":false,"isOut":false,"name":"itemTransaction","tag":"Parameter","type":{"inner":{"index":78973,"kind":"Class","name":"SItemTransaction","tag":"Type"},"kind":"ScriptRef","tag":"Type"}}],"returnType":{"kind":"Prim","name":"Bool","tag":"Type"},"source":"cyberpunk/systems/marketSystem/vendor.script","tag":"Function","visibility":"private"},{"isCallback":false,"isExec":false,"isFinal":true,"isNative":false,"isStatic":false,"name":"AddItemsToStock;script_ref<SItemStack>","parameters":[{"isOptional":false,"isOut":false,"name":"itemStack","tag":"Parameter","type":{"inner":{"index":25061,"kind":"Class","name":"SItemStack","tag":"Type"},"kind":"ScriptRef","tag":"Type"}}],"returnType":null,"source":"cyberpunk/systems/marketSystem/vendor.script","tag":"Function","visibility":"public"},{"isCallback":false,"isExec":false,"isFinal":true,"isNative":false,"isStatic":false,"name":"RemoveItemsFromStock;script_ref<SItemStack>","parameters":[{"isOptional":false,"isOut":false,"name":"itemStack","tag":"Parameter","type":{"inner":{"index":25061,"kind":"Class","name":"SItemStack","tag":"Type"},"kind":"ScriptRef","tag":"Type"}}],"returnType":{"kind":"Prim","name":"Bool","tag":"Type"},"source":"cyberpunk/systems/marketSystem/vendor.script","tag":"Function","visibility":"private"},{"isCallback":false,"isExec":false,"isFinal":true,"isNative":false,"isStatic":false,"name":"GetItemIndex;ItemID","parameters":[{"isOptional":false,"isOut":false,"name":"itemID","tag":"Parameter","type":{"index":21838,"kind":"Class","name":"ItemID","tag":"Type"}}],"returnType":{"kind":"Prim","name":"Int32","tag":"Type"},"source":"cyberpunk/systems/marketSystem/vendor.script","tag":"Function","visibility":"private"},{"isCallback":false,"isExec":false,"isFinal":true,"isNative":false,"isStatic":false,"name":"ItemInspected;TweakDBID","parameters":[{"isOptional":false,"isOut":false,"name":"itemTDBID","tag":"Parameter","type":{"kind":"Prim","name":"TweakDBID","tag":"Type"}}],"returnType":null,"source":"cyberpunk/systems/marketSystem/vendor.script","tag":"Function","visibility":"public"},{"isCallback":false,"isExec":false,"isFinal":true,"isNative":false,"isStatic":false,"name":"IsNewItem;TweakDBID","parameters":[{"isOptional":false,"isOut":false,"name":"itemTDBID","tag":"Parameter","type":{"kind":"Prim","name":"TweakDBID","tag":"Type"}}],"returnType":{"kind":"Prim","name":"Bool","tag":"Type"},"source":"cyberpunk/systems/marketSystem/vendor.script","tag":"Function","visibility":"public"},{"isCallback":false,"isExec":false,"isFinal":true,"isNative":false,"isStatic":false,"name":"GetNewItems;","parameters":[],"returnType":{"inner":{"kind":"Prim","name":"TweakDBID","tag":"Type"},"kind":"Array","tag":"Type"},"source":"cyberpunk/systems/marketSystem/vendor.script","tag":"Function","visibility":"public"},{"isCallback":false,"isExec":false,"isFinal":true,"isNative":false,"isStatic":false,"name":"DoesEquipAreaContainNewItems;gamedataEquipmentAreaBool","parameters":[{"isOptional":false,"isOut":false,"name":"area","tag":"Parameter","type":{"index":6443,"kind":"Class","name":"gamedataEquipmentArea","tag":"Type"}},{"isOptional":false,"isOut":false,"name":"checkPlayerCanBuy","tag":"Parameter","type":{"kind":"Prim","name":"Bool","tag":"Type"}}],"returnType":{"kind":"Prim","name":"Bool","tag":"Type"},"source":"cyberpunk/systems/marketSystem/vendor.script","tag":"Function","visibility":"public"}],"name":"Vendor","tag":"Class","visibility":"public"}