{"bases":[],"fields":[{"isConst":false,"isEdit":false,"isInline":false,"isNative":false,"isPersistent":true,"isRep":false,"name":"regularActions","tag":"Field","type":{"kind":"Prim","name":"Bool","tag":"Type"}},{"isConst":false,"isEdit":false,"isInline":false,"isNative":false,"isPersistent":true,"isRep":false,"name":"quickHacks","tag":"Field","type":{"kind":"Prim","name":"Bool","tag":"Type"}},{"isConst":false,"isEdit":false,"isInline":false,"isNative":false,"isPersistent":true,"isRep":false,"name":"skillChecks","tag":"Field","type":{"kind":"Prim","name":"Bool","tag":"Type"}}],"isAbstract":false,"isFinal":false,"isNative":false,"isStruct":true,"methods":[],"name":"IllegalActionTypes","tag":"Class","visibility":"public"}