{"isCallback":false,"isExec":false,"isFinal":false,"isNative":false,"isStatic":true,"name":"OperatorGreater;ESecuritySystemStateESecuritySystemState;Bool","parameters":[{"isOptional":false,"isOut":false,"name":"enum1","tag":"Parameter","type":{"index":8732,"kind":"Class","name":"ESecuritySystemState","tag":"Type"}},{"isOptional":false,"isOut":false,"name":"enum2","tag":"Parameter","type":{"index":8732,"kind":"Class","name":"ESecuritySystemState","tag":"Type"}}],"returnType":{"kind":"Prim","name":"Bool","tag":"Type"},"source":"cyberpunk/devices/masters/systems/securitySystem/securitySystemMisc.script","tag":"Function","visibility":"public"}