{"bases":[{"base":null,"index":28090,"name":"ActionBool"},{"base":null,"index":18305,"name":"ScriptableDeviceAction"},{"base":null,"index":18160,"name":"BaseScriptableAction"},{"base":null,"index":18059,"name":"DeviceAction"},{"base":null,"index":11485,"name":"Event"},{"base":null,"index":11333,"name":"IScriptable"}],"fields":[],"isAbstract":false,"isFinal":false,"isNative":false,"isStruct":false,"methods":[{"isCallback":false,"isExec":false,"isFinal":true,"isNative":false,"isStatic":false,"name":"SetProperties;Bool","parameters":[{"isOptional":false,"isOut":false,"name":"toggle","tag":"Parameter","type":{"kind":"Prim","name":"Bool","tag":"Type"}}],"returnType":null,"source":"cyberpunk/devices/elevator/liftController.script","tag":"Function","visibility":"public"}],"name":"QuestDisableRadio","tag":"Class","visibility":"public"}