{"bases":[{"base":null,"index":23480,"name":"AIEvent"},{"base":null,"index":10059,"name":"Event"},{"base":null,"index":9320,"name":"IScriptable"}],"fields":[{"isConst":false,"isEdit":false,"isInline":false,"isNative":false,"isPersistent":false,"isRep":false,"name":"bodyPart","tag":"Field","type":{"index":1989,"kind":"Class","name":"gameDismBodyPart","tag":"Type"}},{"isConst":false,"isEdit":false,"isInline":false,"isNative":false,"isPersistent":false,"isRep":false,"name":"dismembermentType","tag":"Field","type":{"index":1996,"kind":"Class","name":"gameDismWoundType","tag":"Type"}},{"isConst":false,"isEdit":false,"isInline":false,"isNative":false,"isPersistent":false,"isRep":false,"name":"hitPosition","tag":"Field","type":{"index":22329,"kind":"Class","name":"Vector4","tag":"Type"}},{"isConst":false,"isEdit":false,"isInline":false,"isNative":false,"isPersistent":false,"isRep":false,"name":"isCritical","tag":"Field","type":{"kind":"Prim","name":"Bool","tag":"Type"}}],"isAbstract":false,"isFinal":false,"isNative":false,"isStruct":false,"methods":[],"name":"RequestDismembermentEvent","tag":"Class","visibility":"public"}