{"bases":[{"base":null,"index":26738,"name":"ScriptableComponent"},{"base":null,"index":17932,"name":"GameComponent"},{"base":null,"index":17899,"name":"IComponent"},{"base":null,"index":11333,"name":"IScriptable"}],"fields":[{"isConst":false,"isEdit":false,"isInline":false,"isNative":false,"isPersistent":false,"isRep":false,"name":"m_scavengeTargets","tag":"Field","type":{"inner":{"inner":{"index":11500,"kind":"Class","name":"GameObject","tag":"Type"},"kind":"WeakRef","tag":"Type"},"kind":"Array","tag":"Type"}}],"isAbstract":false,"isFinal":false,"isNative":false,"isStruct":false,"methods":[{"isCallback":false,"isExec":false,"isFinal":true,"isNative":false,"isStatic":false,"name":"OnGameAttach;","parameters":[],"returnType":null,"source":"core/components/scriptComponents/scavengeComponent.script","tag":"Function","visibility":"public"},{"isCallback":true,"isExec":false,"isFinal":false,"isNative":false,"isStatic":false,"name":"OnSenseVisibilityEvent","parameters":[{"isOptional":false,"isOut":false,"name":"evt","tag":"Parameter","type":{"inner":{"index":44538,"kind":"Class","name":"SenseVisibilityEvent","tag":"Type"},"kind":"Ref","tag":"Type"}}],"returnType":{"kind":"Prim","name":"Bool","tag":"Type"},"source":"core/components/scriptComponents/scavengeComponent.script","tag":"Function","visibility":"protected"},{"isCallback":true,"isExec":false,"isFinal":false,"isNative":false,"isStatic":false,"name":"OnScavengeTargetReceived","parameters":[{"isOptional":false,"isOut":false,"name":"evt","tag":"Parameter","type":{"inner":{"index":27272,"kind":"Class","name":"ScavengeTargetConfirmEvent","tag":"Type"},"kind":"Ref","tag":"Type"}}],"returnType":{"kind":"Prim","name":"Bool","tag":"Type"},"source":"core/components/scriptComponents/scavengeComponent.script","tag":"Function","visibility":"protected"},{"isCallback":true,"isExec":false,"isFinal":false,"isNative":false,"isStatic":false,"name":"OnTargetScavenged","parameters":[{"isOptional":false,"isOut":false,"name":"evt","tag":"Parameter","type":{"inner":{"index":27285,"kind":"Class","name":"TargetScavengedEvent","tag":"Type"},"kind":"Ref","tag":"Type"}}],"returnType":{"kind":"Prim","name":"Bool","tag":"Type"},"source":"core/components/scriptComponents/scavengeComponent.script","tag":"Function","visibility":"protected"},{"isCallback":false,"isExec":false,"isFinal":true,"isNative":false,"isStatic":false,"name":"GetScavengeTargets;","parameters":[],"returnType":{"inner":{"inner":{"index":11500,"kind":"Class","name":"GameObject","tag":"Type"},"kind":"WeakRef","tag":"Type"},"kind":"Array","tag":"Type"},"source":"core/components/scriptComponents/scavengeComponent.script","tag":"Function","visibility":"public"}],"name":"ScavengeComponent","tag":"Class","visibility":"public"}