{"bases":[],"fields":[{"isConst":false,"isEdit":false,"isInline":false,"isNative":false,"isPersistent":false,"isRep":false,"name":"delay","tag":"Field","type":{"kind":"Prim","name":"Float","tag":"Type"}},{"isConst":false,"isEdit":false,"isInline":false,"isNative":false,"isPersistent":false,"isRep":false,"name":"resetDelay","tag":"Field","type":{"kind":"Prim","name":"Bool","tag":"Type"}},{"isConst":false,"isEdit":false,"isInline":false,"isNative":false,"isPersistent":false,"isRep":false,"name":"executeOnce","tag":"Field","type":{"kind":"Prim","name":"Bool","tag":"Type"}},{"isConst":false,"isEdit":false,"isInline":false,"isNative":false,"isPersistent":false,"isRep":false,"name":"isEnabled","tag":"Field","type":{"kind":"Prim","name":"Bool","tag":"Type"}},{"isConst":true,"isEdit":false,"isInline":false,"isNative":false,"isPersistent":false,"isRep":false,"name":"transformAnimations","tag":"Field","type":{"inner":{"index":66382,"kind":"Class","name":"STransformAnimationData","tag":"Type"},"kind":"Array","tag":"Type"}},{"isConst":true,"isEdit":false,"isInline":false,"isNative":false,"isPersistent":false,"isRep":false,"name":"VFXs","tag":"Field","type":{"inner":{"index":66306,"kind":"Class","name":"SVFXOperationData","tag":"Type"},"kind":"Array","tag":"Type"}},{"isConst":true,"isEdit":false,"isInline":false,"isNative":false,"isPersistent":false,"isRep":false,"name":"SFXs","tag":"Field","type":{"inner":{"index":66342,"kind":"Class","name":"SSFXOperationData","tag":"Type"},"kind":"Array","tag":"Type"}},{"isConst":true,"isEdit":false,"isInline":false,"isNative":false,"isPersistent":false,"isRep":false,"name":"facts","tag":"Field","type":{"inner":{"index":66349,"kind":"Class","name":"SFactOperationData","tag":"Type"},"kind":"Array","tag":"Type"}},{"isConst":true,"isEdit":false,"isInline":false,"isNative":false,"isPersistent":false,"isRep":false,"name":"components","tag":"Field","type":{"inner":{"index":66359,"kind":"Class","name":"SComponentOperationData","tag":"Type"},"kind":"Array","tag":"Type"}},{"isConst":true,"isEdit":false,"isInline":false,"isNative":false,"isPersistent":false,"isRep":false,"name":"stims","tag":"Field","type":{"inner":{"index":66415,"kind":"Class","name":"SStimOperationData","tag":"Type"},"kind":"Array","tag":"Type"}},{"isConst":true,"isEdit":false,"isInline":false,"isNative":false,"isPersistent":false,"isRep":false,"name":"statusEffects","tag":"Field","type":{"inner":{"index":66427,"kind":"Class","name":"SStatusEffectOperationData","tag":"Type"},"kind":"Array","tag":"Type"}},{"isConst":true,"isEdit":false,"isInline":false,"isNative":false,"isPersistent":false,"isRep":false,"name":"damages","tag":"Field","type":{"inner":{"index":66445,"kind":"Class","name":"SDamageOperationData","tag":"Type"},"kind":"Array","tag":"Type"}},{"isConst":true,"isEdit":false,"isInline":false,"isNative":false,"isPersistent":false,"isRep":false,"name":"items","tag":"Field","type":{"inner":{"index":66455,"kind":"Class","name":"SInventoryOperationData","tag":"Type"},"kind":"Array","tag":"Type"}},{"isConst":false,"isEdit":false,"isInline":false,"isNative":false,"isPersistent":false,"isRep":false,"name":"teleport","tag":"Field","type":{"index":66471,"kind":"Class","name":"STeleportOperationData","tag":"Type"}},{"isConst":false,"isEdit":false,"isInline":false,"isNative":false,"isPersistent":false,"isRep":false,"name":"meshesAppearence","tag":"Field","type":{"kind":"Prim","name":"CName","tag":"Type"}},{"isConst":false,"isEdit":false,"isInline":false,"isNative":false,"isPersistent":false,"isRep":false,"name":"playerWorkspot","tag":"Field","type":{"index":66403,"kind":"Class","name":"SWorkspotData","tag":"Type"}},{"isConst":false,"isEdit":false,"isInline":false,"isNative":false,"isPersistent":false,"isRep":false,"name":"disableDevice","tag":"Field","type":{"kind":"Prim","name":"Bool","tag":"Type"}},{"isConst":true,"isEdit":false,"isInline":false,"isNative":false,"isPersistent":false,"isRep":false,"name":"toggleOperations","tag":"Field","type":{"inner":{"index":66477,"kind":"Class","name":"SToggleOperationData","tag":"Type"},"kind":"Array","tag":"Type"}},{"isConst":false,"isEdit":false,"isInline":false,"isNative":false,"isPersistent":false,"isRep":false,"name":"id","tag":"Field","type":{"kind":"Prim","name":"Int32","tag":"Type"}},{"isConst":false,"isEdit":false,"isInline":false,"isNative":false,"isPersistent":false,"isRep":false,"name":"delayID","tag":"Field","type":{"index":45801,"kind":"Class","name":"DelayID","tag":"Type"}},{"isConst":false,"isEdit":false,"isInline":false,"isNative":false,"isPersistent":false,"isRep":false,"name":"isDelayActive","tag":"Field","type":{"kind":"Prim","name":"Bool","tag":"Type"}}],"isAbstract":false,"isFinal":false,"isNative":false,"isStruct":true,"methods":[],"name":"SBaseDeviceOperationData","tag":"Class","visibility":"public"}