{"bases":[{"base":null,"index":23264,"name":"ScriptableComponent"},{"base":null,"index":15041,"name":"GameComponent"},{"base":null,"index":15009,"name":"IComponent"},{"base":null,"index":9320,"name":"IScriptable"}],"fields":[],"isAbstract":false,"isFinal":false,"isNative":false,"isStruct":false,"methods":[{"isCallback":false,"isExec":false,"isFinal":true,"isNative":false,"isStatic":false,"name":"OnGameAttach;","parameters":[],"returnType":null,"source":"cyberpunk/devices/phone.script","tag":"Function","visibility":"private"},{"isCallback":false,"isExec":false,"isFinal":true,"isNative":false,"isStatic":false,"name":"OnGameDetach;","parameters":[],"returnType":null,"source":"cyberpunk/devices/phone.script","tag":"Function","visibility":"private"}],"name":"PlayerPhone","tag":"Class","visibility":"public"}